{
  "_id": "C3dE4fF5gH6iJ7kL",
  "_key": "!items!C3dE4fF5gH6iJ7kL",
  "name": "Persuasão",
  "type": "skill",
  "img": "icons/skills/social/diplomacy-handshake.webp",
  "system": {
    "skillDescription": "Capacidade de influenciar outros através de argumentos convincentes, carisma pessoal e habilidade de negociação. Útil para resolver conflitos pacificamente e obter cooperação.",
    "skillType": "extra",
    "description": "<p>Capacidade de influenciar outros através de argumentos convincentes, carisma pessoal e habilidade de negociação. Útil para resolver conflitos pacificamente e obter cooperação.</p>"
  },
  "effects": [],
  "folder": null,
  "flags": {},
  "_stats": {
    "coreVersion": "12.328",
    "systemId": "cardigan",
    "systemVersion": "3.0.7",
    "createdTime": null,
    "modifiedTime": null,
    "lastModifiedBy": null
  }
}